somappy/__init__.py
somappy/som_selector.py
somappy/som_selector_gui.py
somappy/somutils.py
somappy-0.1.0.dist-info/LICENSE
somappy-0.1.0.dist-info/METADATA
somappy-0.1.0.dist-info/WHEEL
somappy-0.1.0.dist-info/entry_points.txt
somappy-0.1.0.dist-info/top_level.txt
somappy-0.1.0.dist-info/RECORD
