Metadata-Version: 2.1
Name: somappy
Version: 0.1.0
Summary: A Self Organizing Map library based on R-Kohonen.
Home-page: https://github.com/dcdenu4/somappy
Author: Doug Denu
Author-email: dcdenu4@gmail.com
License: UNKNOWN
Platform: UNKNOWN
Classifier: Programming Language :: Python :: 3
Classifier: License :: OSI Approved :: MIT License
Classifier: Operating System :: OS Independent
Requires-Python: >=3.7
